facade_selenium/__init__.py
facade_selenium/main.py
facade_selenium-0.0.1.dist-info/METADATA
facade_selenium-0.0.1.dist-info/WHEEL
facade_selenium-0.0.1.dist-info/entry_points.txt
facade_selenium-0.0.1.dist-info/top_level.txt
facade_selenium-0.0.1.dist-info/RECORD
