Metadata-Version: 2.1
Name: facade-selenium
Version: 0.0.1
